fusion_review/__init__.py
fusion_review/__main__.py
fusion_review/figpan.py
fusion_review/intensities.py
fusion_review/itrace.py
fusion_review/multiprocutils.py
fusion_review/utilog.py
fusion_review-0.6.0.dist-info/LICENSE.txt
fusion_review-0.6.0.dist-info/METADATA
fusion_review-0.6.0.dist-info/WHEEL
fusion_review-0.6.0.dist-info/top_level.txt
fusion_review-0.6.0.dist-info/RECORD
